emp_orderly/__init__.py
emp_orderly/account.py
emp_orderly/auth.py
emp_orderly/exceptions.py
emp_orderly/history.py
emp_orderly/liquidation.py
emp_orderly/logger.py
emp_orderly/message_types.py
emp_orderly/order_book.py
emp_orderly/strategy.py
emp_orderly/sync.py
emp_orderly/backtest/__init__.py
emp_orderly/backtest/_plotting.py
emp_orderly/backtest/_stats.py
emp_orderly/backtest/_util.py
emp_orderly/backtest/autoscale_cb.js
emp_orderly/backtest/backtesting.py
emp_orderly/backtest/lib.py
emp_orderly/backtest/indicators/__init__.py
emp_orderly/backtest/indicators/moving_average.py
emp_orderly/backtest/strategies/__init__.py
emp_orderly/backtest/strategies/mean_reversion.py
emp_orderly/backtest/strategies/sma.py
emp_orderly/onboarding/__init__.py
emp_orderly/onboarding/add_access_key.py
emp_orderly/onboarding/create_account.py
emp_orderly/onboarding/deposit.py
emp_orderly/onboarding/faucet.py
emp_orderly/types/__init__.py
emp_orderly/types/domains.py
emp_orderly/utils/__init__.py
emp_orderly/utils/deposit.py
emp_orderly/utils/ed25519.py
emp_orderly/utils/orderly_id.py
emp_orderly/utils/register.py
emp_orderly/utils/signer.py
emp_orderly/utils/timestamp.py
emp_orderly-1.0.dist-info/METADATA
emp_orderly-1.0.dist-info/WHEEL
emp_orderly-1.0.dist-info/top_level.txt
emp_orderly-1.0.dist-info/RECORD
